<annotation>
	<folder>700</folder>
	<filename>may21_31to33C_530pm_53519.png</filename>
	<path>C:\Users\86131\Desktop\700\may21_31to33C_530pm_53519.png</path>
	<source>
		<database>Unknown</database>
	</source>
	<size>
		<width>640</width>
		<height>512</height>
		<depth>1</depth>
	</size>
	<segmented>0</segmented>
	<object>
		<name>car</name>
		<pose>Unspecified</pose>
		<truncated>0</truncated>
		<difficult>0</difficult>
		<bndbox>
			<xmin>313</xmin>
			<ymin>128</ymin>
			<xmax>350</xmax>
			<ymax>154</ymax>
		</bndbox>
	</object>
	<object>
		<name>car</name>
		<pose>Unspecified</pose>
		<truncated>0</truncated>
		<difficult>0</difficult>
		<bndbox>
			<xmin>390</xmin>
			<ymin>137</ymin>
			<xmax>430</xmax>
			<ymax>168</ymax>
		</bndbox>
	</object>
	<object>
		<name>car</name>
		<pose>Unspecified</pose>
		<truncated>0</truncated>
		<difficult>0</difficult>
		<bndbox>
			<xmin>409</xmin>
			<ymin>126</ymin>
			<xmax>435</xmax>
			<ymax>144</ymax>
		</bndbox>
	</object>
	<object>
		<name>car</name>
		<pose>Unspecified</pose>
		<truncated>0</truncated>
		<difficult>0</difficult>
		<bndbox>
			<xmin>469</xmin>
			<ymin>124</ymin>
			<xmax>492</xmax>
			<ymax>140</ymax>
		</bndbox>
	</object>
	<object>
		<name>car</name>
		<pose>Unspecified</pose>
		<truncated>1</truncated>
		<difficult>0</difficult>
		<bndbox>
			<xmin>549</xmin>
			<ymin>130</ymin>
			<xmax>640</xmax>
			<ymax>159</ymax>
		</bndbox>
	</object>
</annotation>
