<annotation>
	<folder>IR_driving_dataset_final</folder>
	<filename>may21_31to33C_530pm_17027.png</filename>
	<path>F:\jz\IR_driving_dataset_final\IR_driving_dataset_final\may21_31to33C_530pm_17027.png</path>
	<source>
		<database>Unknown</database>
	</source>
	<size>
		<width>640</width>
		<height>512</height>
		<depth>1</depth>
	</size>
	<segmented>0</segmented>
	<object>
		<name>car</name>
		<pose>Unspecified</pose>
		<truncated>0</truncated>
		<difficult>0</difficult>
		<bndbox>
			<xmin>2</xmin>
			<ymin>120</ymin>
			<xmax>200</xmax>
			<ymax>367</ymax>
		</bndbox>
	</object>
	<object>
		<name>car</name>
		<pose>Unspecified</pose>
		<truncated>0</truncated>
		<difficult>0</difficult>
		<bndbox>
			<xmin>159</xmin>
			<ymin>145</ymin>
			<xmax>215</xmax>
			<ymax>170</ymax>
		</bndbox>
	</object>
	<object>
		<name>car</name>
		<pose>Unspecified</pose>
		<truncated>0</truncated>
		<difficult>0</difficult>
		<bndbox>
			<xmin>204</xmin>
			<ymin>144</ymin>
			<xmax>233</xmax>
			<ymax>168</ymax>
		</bndbox>
	</object>
	<object>
		<name>car</name>
		<pose>Unspecified</pose>
		<truncated>0</truncated>
		<difficult>0</difficult>
		<bndbox>
			<xmin>277</xmin>
			<ymin>141</ymin>
			<xmax>304</xmax>
			<ymax>154</ymax>
		</bndbox>
	</object>
	<object>
		<name>car</name>
		<pose>Unspecified</pose>
		<truncated>0</truncated>
		<difficult>0</difficult>
		<bndbox>
			<xmin>339</xmin>
			<ymin>146</ymin>
			<xmax>480</xmax>
			<ymax>194</ymax>
		</bndbox>
	</object>
	<object>
		<name>car</name>
		<pose>Unspecified</pose>
		<truncated>0</truncated>
		<difficult>0</difficult>
		<bndbox>
			<xmin>468</xmin>
			<ymin>136</ymin>
			<xmax>571</xmax>
			<ymax>188</ymax>
		</bndbox>
	</object>
	<object>
		<name>car</name>
		<pose>Unspecified</pose>
		<truncated>1</truncated>
		<difficult>0</difficult>
		<bndbox>
			<xmin>493</xmin>
			<ymin>139</ymin>
			<xmax>640</xmax>
			<ymax>191</ymax>
		</bndbox>
	</object>
	<object>
		<name>people</name>
		<pose>Unspecified</pose>
		<truncated>1</truncated>
		<difficult>0</difficult>
		<bndbox>
			<xmin>622</xmin>
			<ymin>132</ymin>
			<xmax>640</xmax>
			<ymax>238</ymax>
		</bndbox>
	</object>
</annotation>
